geojsoncontour/__init__.py
geojsoncontour/contour.py
geojsoncontour/utilities/__init__.py
geojsoncontour/utilities/multipoly.py
geojsoncontour/utilities/netcdfhelper.py
geojsoncontour/utilities/vertices.py
geojsoncontour-0.5.1.dist-info/LICENSE.md
geojsoncontour-0.5.1.dist-info/METADATA
geojsoncontour-0.5.1.dist-info/WHEEL
geojsoncontour-0.5.1.dist-info/top_level.txt
geojsoncontour-0.5.1.dist-info/RECORD
