Metadata-Version: 2.1
Name: geojsoncontour
Version: 0.5.1
Summary: Convert matplotlib contour plots to geojson
Home-page: http://github.com/bartromgens/geojsoncontour
Author: Bart Römgens
Author-email: bart.romgens@gmail.com
License: MIT
Keywords: contour plot geojson pyplot matplotlib gis map
Classifier: Development Status :: 4 - Beta
Classifier: Intended Audience :: Developers
Classifier: License :: OSI Approved :: MIT License
Classifier: Programming Language :: Python :: 3
Classifier: Programming Language :: Python :: 3.4
Classifier: Programming Language :: Python :: 3.5
Classifier: Programming Language :: Python :: 3.6
Classifier: Programming Language :: Python :: 3.7
License-File: LICENSE.md
Requires-Dist: geojson
Requires-Dist: numpy
Requires-Dist: matplotlib>=3.8
Requires-Dist: xarray
